odoo9_addon_purchase_variant_configurator-9.0.1.0.0.99.dev12-py3.8-nspkg.pth
odoo_addons/purchase_variant_configurator/README.rst
odoo_addons/purchase_variant_configurator/__init__.py
odoo_addons/purchase_variant_configurator/__openerp__.py
odoo_addons/purchase_variant_configurator/hooks.py
odoo_addons/purchase_variant_configurator/i18n/es.po
odoo_addons/purchase_variant_configurator/i18n/fr.po
odoo_addons/purchase_variant_configurator/i18n/it.po
odoo_addons/purchase_variant_configurator/i18n/pt_BR.po
odoo_addons/purchase_variant_configurator/i18n/purchase_variant_configurator.pot
odoo_addons/purchase_variant_configurator/i18n/ro.po
odoo_addons/purchase_variant_configurator/i18n/sl.po
odoo_addons/purchase_variant_configurator/migrations/8.0.2.0.0/pre-migration.py
odoo_addons/purchase_variant_configurator/models/__init__.py
odoo_addons/purchase_variant_configurator/models/purchase_order_line.py
odoo_addons/purchase_variant_configurator/static/description/icon.png
odoo_addons/purchase_variant_configurator/tests/__init__.py
odoo_addons/purchase_variant_configurator/tests/test_purchase_order.py
odoo_addons/purchase_variant_configurator/views/inherited_product_product_views.xml
odoo_addons/purchase_variant_configurator/views/inherited_purchase_order_views.xml
odoo9_addon_purchase_variant_configurator-9.0.1.0.0.99.dev12.dist-info/METADATA
odoo9_addon_purchase_variant_configurator-9.0.1.0.0.99.dev12.dist-info/WHEEL
odoo9_addon_purchase_variant_configurator-9.0.1.0.0.99.dev12.dist-info/namespace_packages.txt
odoo9_addon_purchase_variant_configurator-9.0.1.0.0.99.dev12.dist-info/top_level.txt
odoo9_addon_purchase_variant_configurator-9.0.1.0.0.99.dev12.dist-info/RECORD
